LICENSE.txt
MANIFEST.in
README.md
requirements.txt
setup.py
./stringcheese/pyahocorasick-1.4.0/pyahocorasick.c
stringcheese/__init__.py
stringcheese/stringcheese.py
stringcheese.egg-info/PKG-INFO
stringcheese.egg-info/SOURCES.txt
stringcheese.egg-info/dependency_links.txt
stringcheese.egg-info/entry_points.txt
stringcheese.egg-info/not-zip-safe
stringcheese.egg-info/requires.txt
stringcheese.egg-info/top_level.txt
stringcheese/pyahocorasick-1.4.0/.gitignore
stringcheese/pyahocorasick-1.4.0/.travis.yml
stringcheese/pyahocorasick-1.4.0/Automaton.c
stringcheese/pyahocorasick-1.4.0/Automaton.h
stringcheese/pyahocorasick-1.4.0/AutomatonItemsIter.c
stringcheese/pyahocorasick-1.4.0/AutomatonItemsIter.h
stringcheese/pyahocorasick-1.4.0/AutomatonSearchIter.c
stringcheese/pyahocorasick-1.4.0/AutomatonSearchIter.h
stringcheese/pyahocorasick-1.4.0/AutomatonSearchIterLong.c
stringcheese/pyahocorasick-1.4.0/AutomatonSearchIterLong.h
stringcheese/pyahocorasick-1.4.0/Automaton_pickle.c
stringcheese/pyahocorasick-1.4.0/CHANGELOG.rst
stringcheese/pyahocorasick-1.4.0/LICENSE
stringcheese/pyahocorasick-1.4.0/MANIFEST.in
stringcheese/pyahocorasick-1.4.0/Makefile
stringcheese/pyahocorasick-1.4.0/README.rst
stringcheese/pyahocorasick-1.4.0/allsources.c
stringcheese/pyahocorasick-1.4.0/appveyor.yml
stringcheese/pyahocorasick-1.4.0/common.h
stringcheese/pyahocorasick-1.4.0/cygwin.h
stringcheese/pyahocorasick-1.4.0/dump2dot.py
stringcheese/pyahocorasick-1.4.0/posix.h
stringcheese/pyahocorasick-1.4.0/pyahocorasick.c
stringcheese/pyahocorasick-1.4.0/setup.cfg
stringcheese/pyahocorasick-1.4.0/setup.py
stringcheese/pyahocorasick-1.4.0/slist.c
stringcheese/pyahocorasick-1.4.0/slist.h
stringcheese/pyahocorasick-1.4.0/test.py
stringcheese/pyahocorasick-1.4.0/trie.c
stringcheese/pyahocorasick-1.4.0/trie.h
stringcheese/pyahocorasick-1.4.0/trienode.c
stringcheese/pyahocorasick-1.4.0/trienode.h
stringcheese/pyahocorasick-1.4.0/unittests.py
stringcheese/pyahocorasick-1.4.0/unpickle_test.py
stringcheese/pyahocorasick-1.4.0/update_inlinedoc.py
stringcheese/pyahocorasick-1.4.0/utils.c
stringcheese/pyahocorasick-1.4.0/windows.bat
stringcheese/pyahocorasick-1.4.0/windows.h
stringcheese/pyahocorasick-1.4.0/benchmarks/benchmark.py
