Metadata-Version: 2.1
Name: stringcheese
Version: 2.1
Summary: StringCheese is a tool to get easy CTF flags automatically.
Home-page: https://github.com/MathisHammel/stringcheese
Author: MathisHammel
Author-email: mathis@h25.io
License: GPL2
Platform: UNKNOWN
License-File: LICENSE.txt
